MANIFEST.in
README
setup.py
pybiosas/__init__.py
pybiosas/modelling.py
pybiosas/models.py
pybiosas/sas_utils.py
pybiosas/version.py
pybiosas.egg-info/PKG-INFO
pybiosas.egg-info/SOURCES.txt
pybiosas.egg-info/dependency_links.txt
pybiosas.egg-info/requires.txt
pybiosas.egg-info/top_level.txt
test/__init__.py
test/test.json
test/test_data_coreshellbicelle.xml
test/test_data_cylinder.xml
test/test_data_ellipse.xml
test/test_data_sphere.xml
test/test_modelfit.py
test/testdata.xml