Metadata-Version: 1.0
Name: pybiosas
Version: 0.2.0
Summary: Library of SANS model fitting and management tools
Home-page: https://github.com/cameronneylon/contrail
Author: Cameron Neylon
Author-email: pypi@cameroneylon.net
License: UNKNOWN
Platform: UNKNOWN
